LICENSE
MANIFEST.in
README.rst
buildout.cfg
requirements.txt
setup.py
version.txt
bob/__init__.py
bob.ip.caffe_extractor.egg-info/PKG-INFO
bob.ip.caffe_extractor.egg-info/SOURCES.txt
bob.ip.caffe_extractor.egg-info/dependency_links.txt
bob.ip.caffe_extractor.egg-info/requires.txt
bob.ip.caffe_extractor.egg-info/top_level.txt
bob/ip/__init__.py
bob/ip/caffe_extractor/Extractor.py
bob/ip/caffe_extractor/LightCNN.py
bob/ip/caffe_extractor/VGGFace.py
bob/ip/caffe_extractor/__init__.py
bob/ip/caffe_extractor/test.py
bob/ip/caffe_extractor/data/8821.hdf5
bob/ip/caffe_extractor/data/VGG_FACE_deploy.prototxt
bob/ip/caffe_extractor/data/lightcnn_reference_feature.hdf5
bob/ip/caffe_extractor/data/lightcnn_reference_image.hdf5
bob/ip/caffe_extractor/data/reference.hdf5
doc/conf.py
doc/guide.rst
doc/index.rst
doc/py_api.rst
doc/plot/convolve.py