Metadata-Version: 1.1
Name: bob.ip.caffe-extractor
Version: 2.0.3
Summary: Feature extractor using caffe CNNs
Home-page: https://gitlab.idiap.ch/tiago.pereira/bob.bio.caffe_extractor
Author: Tiago de Freitas Pereira
Author-email: tiago.pereira@idiap.ch
License: BSD
Keywords: bob,biometric recognition,evaluation
Platform: UNKNOWN
Classifier: Framework :: Bob
Classifier: Development Status :: 4 - Beta
Classifier: Intended Audience :: Developers
Classifier: License :: OSI Approved :: BSD License
Classifier: Natural Language :: English
Classifier: Programming Language :: Python
Classifier: Topic :: Scientific/Engineering :: Artificial Intelligence
